ghost/__init__.py
ghost/__main__.py
ghost/config.py
ghost/encryption.py
ghost/key.py
ghost/stream.py
ghost/data/.config
ghost/data/.register
ghost_encrypt-1.0.6.dist-info/LICENSE
ghost_encrypt-1.0.6.dist-info/METADATA
ghost_encrypt-1.0.6.dist-info/WHEEL
ghost_encrypt-1.0.6.dist-info/entry_points.txt
ghost_encrypt-1.0.6.dist-info/top_level.txt
ghost_encrypt-1.0.6.dist-info/RECORD
