Metadata-Version: 2.1
Name: ghost-encrypt
Version: 1.0.6
Summary: Cross-Platform tool for de-/encrypting strings, files and sock-streams. Still in development
Home-page: https://github.com/NightKylo/ghost
Author: Marius Kraus
License: Apache
Platform: UNKNOWN
Classifier: License :: OSI Approved :: Apache Software License
Classifier: Programming Language :: Python :: 3
Classifier: Programming Language :: Python :: 3.9
Requires-Dist: arg-parser
